pyudon/__init__.py
pyudon/clustering_wrapper.py
pyudon/enrichment_pathwaycommons.py
pyudon/feature_selection.py
pyudon/linearSVM.py
pyudon/metadata_analysis.py
pyudon/nmf.py
pyudon/pre_process.py
pyudon/satay_udon.py
pyudon/visualizations.py
pyudon/datasets/__init__.py
pyudon/datasets/loaders.py
pyudon-0.0.4.dist-info/licenses/LICENSE
pyudon-0.0.4.dist-info/METADATA
pyudon-0.0.4.dist-info/WHEEL
pyudon-0.0.4.dist-info/top_level.txt
pyudon-0.0.4.dist-info/RECORD
