Metadata-Version: 2.4
Name: pyudon
Version: 0.0.4
Summary: Unsupervised Discovery of Novel Disease Programs
Author-email: Kairavee Thakkar <kairavee.thakkar@cchmc.org>, Nathan Salomonis <nathan.salomonis@cchmc.org>
License-Expression: MIT
Project-URL: Repository, https://github.com/kairaveet/pyudon
Project-URL: Issues, https://github.com/kairaveet/pyudon/issues
Classifier: Programming Language :: Python :: 3
Classifier: Operating System :: OS Independent
Requires-Python: >=3.10
License-File: LICENSE
Requires-Dist: scanpy==1.9.5
Requires-Dist: numpy==1.24.4
Requires-Dist: scikit-learn==1.3.0
Requires-Dist: pandas==2.1.0
Requires-Dist: nimfa==1.4.0
Requires-Dist: statsmodels==0.14.0
Requires-Dist: tqdm==4.66.1
Requires-Dist: seaborn==0.12.2
Requires-Dist: matplotlib==3.7.2
Requires-Dist: pooch
Requires-Dist: tarfile
Dynamic: license-file
